messaging/__init__.py
messaging/email/__init__.py
messaging/email/attachment.py
messaging/email/mailbag.py
sender/__init__.py
sender/sender.py
transport/__init__.py
transport/request_executor.py
transport/api/__init__.py
transport/api/email.py
freshmail_api_pwd_123673_freshmail.pl-0.7.dist-info/METADATA
freshmail_api_pwd_123673_freshmail.pl-0.7.dist-info/WHEEL
freshmail_api_pwd_123673_freshmail.pl-0.7.dist-info/top_level.txt
freshmail_api_pwd_123673_freshmail.pl-0.7.dist-info/RECORD
