Metadata-Version: 2.1
Name: freshmail-api-pwd-123673-freshmail.pl
Version: 0.7
Summary: FreshMail Python Client
Home-page: https://github.com/FreshMail/Python-Api-Client
Author: FreshMail
Author-email: pomoc@freshmail.pl
License: UNKNOWN
Platform: UNKNOWN
Classifier: Programming Language :: Python :: 3
Classifier: License :: OSI Approved :: MIT License
Classifier: Operating System :: OS Independent
Requires-Python: >=3.5
